voicegpt/__init__.py
voicegpt/hello.py
voicegpt-0.1.0.dist-info/LICENSE
voicegpt-0.1.0.dist-info/METADATA
voicegpt-0.1.0.dist-info/WHEEL
voicegpt-0.1.0.dist-info/RECORD
